fuzzy_system.py
python_fuzzy_system.py
fuzzy_systems-0.3.0.dist-info/LICENSE
fuzzy_systems-0.3.0.dist-info/METADATA
fuzzy_systems-0.3.0.dist-info/WHEEL
fuzzy_systems-0.3.0.dist-info/top_level.txt
fuzzy_systems-0.3.0.dist-info/RECORD
