Metadata-Version: 2.1
Name: fuzzy-systems
Version: 0.3.0
Summary: A fuzzy system for python with fuzzy reasoning and classification.
Home-page: https://github.com/byteofsoren/python_fuzzy_system
Author: Magnus Sörensen
Author-email: byteofsoren@gmail.com
License: UNKNOWN
Platform: UNKNOWN
Classifier: Programming Language :: Python :: 3
Classifier: Programming Language :: Python :: 3.6
Classifier: Programming Language :: Python :: 3.7
Classifier: Programming Language :: Python :: 3.8
Classifier: License :: OSI Approved :: MIT License
Classifier: Operating System :: POSIX
